{
  "gitSyncId": "642a567737fcef7162643435_6433a3a81e9ff4059b04017d",
  "id": "Manage Leaves_fetch_all_vacations",
  "pluginId": "restapi-plugin",
  "pluginType": "API",
  "unpublishedAction": {
    "actionConfiguration": {
      "autoGeneratedHeaders": [],
      "bodyFormData": [],
      "encodeParamsToggle": true,
      "formData": {
        "apiContentType": "none"
      },
      "headers": [],
      "httpMethod": "GET",
      "paginationType": "NONE",
      "path": "",
      "pluginSpecifiedTemplates": [
        {
          "value": true
        }
      ],
      "queryParameters": [],
      "timeoutInMillisecond": 10000
    },
    "confirmBeforeExecute": false,
    "datasource": {
      "id": "QA Internal Supabase",
      "isAutoGenerated": false,
      "name": "QA Internal Supabase",
      "pluginId": "restapi-plugin"
    },
    "dynamicBindingPathList": [
      {
        "key": "path"
      }
    ],
    "name": "fetch_all_vacations",
    "pageId": "Manage Leaves",
    "runBehaviour": "ON_PAGE_LOAD",
    "userSetOnLoad": false
  }
}