{
  "accentColor": "{{appsmith.theme.colors.primaryColor}}",
  "additionalStaticProps": [
    "level",
    "levelData",
    "prefixMetaWidgetId",
    "metaWidgetId"
  ],
  "animateLoading": true,
  "backgroundColor": "transparent",
  "borderRadius": "{{appsmith.theme.borderRadius.appBorderRadius}}",
  "bottomRow": 48,
  "boxShadow": "none",
  "children": [
    {
      "bottomRow": 440,
      "canExtend": false,
      "containerStyle": "none",
      "detachFromLayout": true,
      "displayName": "Canvas",
      "dropDisabled": true,
      "dynamicBindingPathList": [],
      "flexLayers": [],
      "hideCard": true,
      "isDeprecated": false,
      "isLoading": false,
      "isVisible": true,
      "key": "6r25hgknbu",
      "leftColumn": 0,
      "minHeight": 400,
      "minWidth": 450,
      "noPad": true,
      "openParentPropertyPane": true,
      "parentColumnSpace": 1,
      "parentId": "67hze7ci7x",
      "parentRowSpace": 1,
      "renderMode": "CANVAS",
      "responsiveBehavior": "fill",
      "rightColumn": 186.708984375,
      "topRow": 0,
      "type": "CANVAS_WIDGET",
      "version": 1,
      "widgetId": "ryr5mco6px",
      "widgetName": "Canvas19"
    }
  ],
  "currentItemsView": "{{[]}}",
  "displayName": "List",
  "dynamicBindingPathList": [
    {
      "key": "currentItemsView"
    },
    {
      "key": "selectedItemView"
    },
    {
      "key": "triggeredItemView"
    },
    {
      "key": "primaryKeys"
    },
    {
      "key": "accentColor"
    },
    {
      "key": "borderRadius"
    },
    {
      "key": "listData"
    }
  ],
  "dynamicTriggerPathList": [],
  "enhancements": true,
  "gridType": "vertical",
  "hasMetaWidgets": true,
  "hideCard": false,
  "iconSVG": "/static/media/icon.9925ee17dee37bf1ba7374412563a8a7.svg",
  "isCanvas": true,
  "isDeprecated": false,
  "isLoading": false,
  "isVisible": true,
  "itemBackgroundColor": "#FFFFFF",
  "itemSpacing": 8,
  "key": "md5aa2dnyj",
  "leftColumn": 0,
  "listData": "{{_.orderBy(fetch_my_vacations.data, 'id', 'desc')}}",
  "mainCanvasId": "ryr5mco6px",
  "mainContainerId": "lqtexiwu4v",
  "pageSize": 5,
  "parentColumnSpace": 7.779541015625,
  "parentId": "3eu7t166sb",
  "parentRowSpace": 10,
  "positioning": "fixed",
  "primaryKeys": "{{appliedLeaveList.listData.map((currentItem, currentIndex) => currentItem[\"id\"] )}}",
  "renderMode": "CANVAS",
  "requiresFlatWidgetChildren": true,
  "responsiveBehavior": "fill",
  "rightColumn": 64,
  "selectedItemView": "{{{}}}",
  "templateBottomRow": 16,
  "topRow": 4,
  "triggeredItemView": "{{{}}}",
  "type": "LIST_WIDGET_V2",
  "widgetId": "67hze7ci7x",
  "widgetName": "appliedLeaveList"
}